karp_lex/__init__.py
karp_lex/application/__init__.py
karp_lex/application/dtos/__init__.py
karp_lex/application/dtos/entry_dto.py
karp_lex/domain/__init__.py
karp_lex/domain/entities/__init__.py
karp_lex/tests/__init__.py
karp_lex/tests/conftest.py
karp_lex/tests/value_objects_unique_id_test.py
karp_lex/value_objects/__init__.py
karp_lex/value_objects/unique_id.py
karp_lex-0.1.4.dist-info/WHEEL
karp_lex-0.1.4.dist-info/METADATA
karp_lex-0.1.4.dist-info/license_files/LICENSE
karp_lex-0.1.4.dist-info/RECORD
