Metadata-Version: 2.1
Name: karp-lex
Version: 0.1.4
Summary: The domain of the lexical platform Karp
License: MIT
Author-email: Kristoffer Andersson <kristoffer.andersson@gu.se>
Requires-Python: >=3.10
Requires-Dist: pydantic>=1.10.2
Requires-Dist: ulid-py>=1.1.0
Project-URL: Bug Tracker, https://github.com/spraakbanken/karp-lex/issues
Project-URL: changelog, https://github.com/spraakbanken/karp-lex/blob/main/CHANGELOG.md
Project-URL: homepage, https://github.com/spraakbanken/karp-lex
Project-URL: repository, https://github.com/spraakbanken/karp-lex
